pshell/__init__.py
pshell/call.py
pshell/env.py
pshell/file.py
pshell/log.py
pshell/manipulate.py
pshell/open.py
pshell/procs.py
pshell/py.typed
pshell/search.py
pshell/tests/__init__.py
pshell/tests/conftest.py
pshell/tests/test_call.py
pshell/tests/test_env.py
pshell/tests/test_file.py
pshell/tests/test_log.py
pshell/tests/test_manipulate.py
pshell/tests/test_open.py
pshell/tests/test_procs.py
pshell/tests/test_search.py
pshell/tests/data/exit1.bat
pshell/tests/data/hello.bat
pshell/tests/data/sleep20.py
pshell/tests/data/sleep20_sigterm_delay5.py
pshell/tests/data/sleep20_sigterm_ignore.py
pshell/tests/data/source.sh
pshell-1.6.0.dist-info/METADATA
pshell-1.6.0.dist-info/WHEEL
pshell-1.6.0.dist-info/licenses/LICENSE
pshell-1.6.0.dist-info/RECORD
