Metadata-Version: 2.4
Name: pshell
Version: 1.6.0
Summary: An alternative to bash scripts
Project-URL: homepage, https://github.com/crusaderky/pshell
Project-URL: issues, https://github.com/crusaderky/pshell/issues
Project-URL: documentation, https://pshell.readthedocs.io/
Project-URL: changelog, https://pshell.readthedocs.io/en/latest/whats-new.html
Author-email: Guido Imperiale <crusaderky@gmail.com>
License-Expression: Apache-2.0
License-File: LICENSE
Keywords: bash,shell
Classifier: Development Status :: 5 - Production/Stable
Classifier: Intended Audience :: Information Technology
Classifier: Operating System :: OS Independent
Classifier: Programming Language :: Python
Classifier: Programming Language :: Python :: 3
Classifier: Programming Language :: Python :: 3 :: Only
Classifier: Programming Language :: Python :: 3.8
Classifier: Programming Language :: Python :: 3.9
Classifier: Programming Language :: Python :: 3.10
Classifier: Programming Language :: Python :: 3.11
Classifier: Programming Language :: Python :: 3.12
Classifier: Programming Language :: Python :: 3.13
Classifier: Programming Language :: Python :: 3.14
Classifier: Programming Language :: Python :: Free Threading :: 3 - Stable
Classifier: Topic :: System :: System Shells
Requires-Python: >=3.8
Requires-Dist: psutil>=5.7
Provides-Extra: zstd
Requires-Dist: backports-zstd; (python_version < '3.14') and extra == 'zstd'
